<?xml version="1.0" encoding="UTF-8" standalone="yes"?>
<AssignMessage async="false" continueOnError="false" enabled="true" name="Assign-Message-500-JS-Policy-Error-Variables">
    <DisplayName>Assign-Message-500-JS-Policy-Error-Variables</DisplayName>
    <Properties/>
    <Properties/>
    <AssignVariable>
        <Name>flow.error.code</Name>
        <Value>500.003.000</Value>
    </AssignVariable>
    <AssignVariable>
        <Name>flow.error.message</Name>
        <Value>internal server error</Value>
    </AssignVariable>
    <AssignVariable>
        <Name>flow.error.url</Name>
        <Value>https://docs.developer.com</Value>
    </AssignVariable>
    <AssignVariable>
        <Name>flow.error.status</Name>
        <Value>500</Value>
    </AssignVariable>
    <AssignVariable>
        <Name>flow.error.reason</Name>
        <Value>Internal Server Error</Value>
    </AssignVariable>
</AssignMessage>